toretools/__init__.py
toretools/__version__.py
toretools/builtins.py
toretools/toretools.py
toretools/trand.py
toretools-1.0.0.dist-info/METADATA
toretools-1.0.0.dist-info/WHEEL
toretools-1.0.0.dist-info/top_level.txt
toretools-1.0.0.dist-info/RECORD
